main.py
envlock-1.0.0.dist-info/licenses/LICENSE
envlock-1.0.0.dist-info/METADATA
envlock-1.0.0.dist-info/WHEEL
envlock-1.0.0.dist-info/entry_points.txt
envlock-1.0.0.dist-info/top_level.txt
envlock-1.0.0.dist-info/RECORD
