Metadata-Version: 2.4
Name: envlock
Version: 1.0.0
Summary: A secure CLI tool for encrypting, decrypting, shredding, and rotating secrets files using strong symmetric encryption.
Author-email: Nikhil John <me@nikz.in>
License-Expression: MIT
Project-URL: Homepage, https://github.com/nikhiljohn10/envlock
Project-URL: Issues, https://github.com/nikhiljohn10/envlock/issues
Keywords: encryption,secrets,cli,security,cryptography,locker,vault,file,python
Classifier: Programming Language :: Python :: 3
Classifier: Programming Language :: Python :: 3.11
Classifier: Operating System :: OS Independent
Classifier: Intended Audience :: Developers
Classifier: Environment :: Console
Classifier: Topic :: Security :: Cryptography
Classifier: Topic :: Software Development :: Libraries :: Python Modules
Requires-Python: >=3.11
License-File: LICENSE
Requires-Dist: click>=8.2.1
Requires-Dist: cryptography>=45.0.4
Provides-Extra: test
Requires-Dist: pytest>=8.4.1; extra == "test"
Requires-Dist: pytest-cov>=5.0.0; extra == "test"
Dynamic: license-file
